chonkychunker/__init__.py
chonkychunker/chunker.py
chonkychunker-0.1.1.dist-info/METADATA
chonkychunker-0.1.1.dist-info/WHEEL
chonkychunker-0.1.1.dist-info/licenses/LICENSE
chonkychunker-0.1.1.dist-info/RECORD
