Metadata-Version: 2.4
Name: chonkychunker
Version: 0.1.1
Summary: Ball Tree-based semantic text chunker for vector databases and LangChain
Project-URL: Repository, https://github.com/aravindraju98/chonkychunker
Project-URL: Homepage, https://pypi.org/project/chonkychunker
Author-email: Aravind Raju <aravindraju98@email.com>
License: MIT
License-File: LICENSE
Requires-Python: >=3.7
Requires-Dist: langchain
Requires-Dist: numpy
Requires-Dist: scikit-learn
Requires-Dist: sentence-transformers
